{
  "findings": [
    {
      "gate_id": "temporal_consistency",
      "rule_id": "temporal_phase_mismatch",
      "severity": "warning",
      "description": "Event evt_004 type bidder_interest is grounded only in ['bidding'] blocks.",
      "event_ids": [
        "evt_004"
      ],
      "actor_ids": [
        "advisor_company_a_ib",
        "bidder_company_a"
      ],
      "block_ids": [
        "B008"
      ]
    },
    {
      "gate_id": "temporal_consistency",
      "rule_id": "temporal_phase_mismatch",
      "severity": "warning",
      "description": "Event evt_006 type activist_sale is grounded only in ['bidding'] blocks.",
      "event_ids": [
        "evt_006"
      ],
      "actor_ids": [
        "activist_balch_hill"
      ],
      "block_ids": [
        "B011"
      ]
    },
    {
      "gate_id": "temporal_consistency",
      "rule_id": "temporal_phase_mismatch",
      "severity": "warning",
      "description": "Event evt_007 type activist_sale is grounded only in ['bidding'] blocks.",
      "event_ids": [
        "evt_007"
      ],
      "actor_ids": [
        "activist_balch_hill"
      ],
      "block_ids": [
        "B011"
      ]
    },
    {
      "gate_id": "temporal_consistency",
      "rule_id": "temporal_phase_mismatch",
      "severity": "warning",
      "description": "Event evt_008 type bidder_interest is grounded only in ['bidding'] blocks.",
      "event_ids": [
        "evt_008"
      ],
      "actor_ids": [
        "bidder_company_b"
      ],
      "block_ids": [
        "B014"
      ]
    },
    {
      "gate_id": "temporal_consistency",
      "rule_id": "temporal_phase_mismatch",
      "severity": "warning",
      "description": "Event evt_010 type bidder_interest is grounded only in ['bidding'] blocks.",
      "event_ids": [
        "evt_010"
      ],
      "actor_ids": [
        "bidder_company_c"
      ],
      "block_ids": [
        "B024"
      ]
    },
    {
      "gate_id": "temporal_consistency",
      "rule_id": "temporal_phase_mismatch",
      "severity": "warning",
      "description": "Event evt_011a type target_sale is grounded only in ['bidding'] blocks.",
      "event_ids": [
        "evt_011a"
      ],
      "actor_ids": [
        "target_board_stec"
      ],
      "block_ids": [
        "B029"
      ]
    },
    {
      "gate_id": "temporal_consistency",
      "rule_id": "temporal_phase_mismatch",
      "severity": "warning",
      "description": "Event evt_012 type ib_retention is grounded only in ['bidding'] blocks.",
      "event_ids": [
        "evt_012"
      ],
      "actor_ids": [
        "advisor_bofa_merrill_lynch",
        "target_board_stec"
      ],
      "block_ids": [
        "B029",
        "B030"
      ]
    },
    {
      "gate_id": "temporal_consistency",
      "rule_id": "temporal_phase_mismatch",
      "severity": "warning",
      "description": "Event evt_013 type target_sale is grounded only in ['bidding'] blocks.",
      "event_ids": [
        "evt_013"
      ],
      "actor_ids": [
        "advisor_bofa_merrill_lynch",
        "target_board_stec"
      ],
      "block_ids": [
        "B032"
      ]
    },
    {
      "gate_id": "temporal_consistency",
      "rule_id": "temporal_phase_mismatch",
      "severity": "warning",
      "description": "Event evt_018 type nda is grounded only in ['outcome'] blocks.",
      "event_ids": [
        "evt_018"
      ],
      "actor_ids": [
        "bidder_wdc"
      ],
      "block_ids": [
        "B036"
      ]
    },
    {
      "gate_id": "temporal_consistency",
      "rule_id": "temporal_phase_mismatch",
      "severity": "warning",
      "description": "Event evt_025 type bidder_interest is grounded only in ['bidding'] blocks.",
      "event_ids": [
        "evt_025"
      ],
      "actor_ids": [
        "bidder_company_h"
      ],
      "block_ids": [
        "B046"
      ]
    },
    {
      "gate_id": "temporal_consistency",
      "rule_id": "temporal_phase_mismatch",
      "severity": "warning",
      "description": "Event evt_031 type final_round_ann is grounded only in ['outcome'] blocks.",
      "event_ids": [
        "evt_031"
      ],
      "actor_ids": [
        "advisor_bofa_merrill_lynch"
      ],
      "block_ids": [
        "B064"
      ]
    },
    {
      "gate_id": "temporal_consistency",
      "rule_id": "temporal_phase_mismatch",
      "severity": "warning",
      "description": "Event evt_033 type proposal is grounded only in ['outcome'] blocks.",
      "event_ids": [
        "evt_033"
      ],
      "actor_ids": [
        "bidder_wdc"
      ],
      "block_ids": [
        "B066"
      ]
    },
    {
      "gate_id": "temporal_consistency",
      "rule_id": "temporal_phase_mismatch",
      "severity": "warning",
      "description": "Event evt_034 type final_round_ext_ann is grounded only in ['outcome'] blocks.",
      "event_ids": [
        "evt_034"
      ],
      "actor_ids": [
        "advisor_bofa_merrill_lynch",
        "target_board_stec"
      ],
      "block_ids": [
        "B068"
      ]
    },
    {
      "gate_id": "temporal_consistency",
      "rule_id": "temporal_phase_mismatch",
      "severity": "warning",
      "description": "Event evt_038 type restarted is grounded only in ['bidding'] blocks.",
      "event_ids": [
        "evt_038"
      ],
      "actor_ids": [
        "bidder_wdc"
      ],
      "block_ids": [
        "B083"
      ]
    },
    {
      "gate_id": "temporal_consistency",
      "rule_id": "temporal_phase_mismatch",
      "severity": "warning",
      "description": "Event evt_042 type bid_press_release is grounded only in ['outcome'] blocks.",
      "event_ids": [
        "evt_042"
      ],
      "actor_ids": [
        "bidder_wdc",
        "target_board_stec"
      ],
      "block_ids": [
        "B102"
      ]
    },
    {
      "gate_id": "cross_event_logic",
      "rule_id": "undated_event_in_sequence",
      "severity": "warning",
      "description": "Event evt_015 (nda) has no parseable date and was excluded from chronological sequence checks.",
      "event_ids": [
        "evt_015"
      ],
      "actor_ids": [
        "bidder_company_d"
      ],
      "block_ids": []
    },
    {
      "gate_id": "cross_event_logic",
      "rule_id": "undated_event_in_sequence",
      "severity": "warning",
      "description": "Event evt_016 (nda) has no parseable date and was excluded from chronological sequence checks.",
      "event_ids": [
        "evt_016"
      ],
      "actor_ids": [
        "bidder_company_f"
      ],
      "block_ids": []
    },
    {
      "gate_id": "cross_event_logic",
      "rule_id": "undated_event_in_sequence",
      "severity": "warning",
      "description": "Event evt_017 (nda) has no parseable date and was excluded from chronological sequence checks.",
      "event_ids": [
        "evt_017"
      ],
      "actor_ids": [
        "bidder_company_g"
      ],
      "block_ids": []
    },
    {
      "gate_id": "cross_event_logic",
      "rule_id": "undated_event_in_sequence",
      "severity": "warning",
      "description": "Event evt_020 (drop) has no parseable date and was excluded from chronological sequence checks.",
      "event_ids": [
        "evt_020"
      ],
      "actor_ids": [
        "bidder_company_f"
      ],
      "block_ids": []
    },
    {
      "gate_id": "cross_event_logic",
      "rule_id": "undated_event_in_sequence",
      "severity": "warning",
      "description": "Event evt_021 (drop) has no parseable date and was excluded from chronological sequence checks.",
      "event_ids": [
        "evt_021"
      ],
      "actor_ids": [
        "bidder_company_e"
      ],
      "block_ids": []
    }
  ],
  "attention_decay": {
    "quartile_counts": [
      0,
      0,
      0,
      0
    ],
    "hot_spots": [],
    "decay_score": 1.0,
    "note": null
  },
  "summary": {
    "blocker_count": 0,
    "warning_count": 20,
    "status": "pass"
  }
}